[
    {
        "month": "Mar",
        "investment": 100000,
        "sell": 241,
        "revenue": 10401,
        "stock": 990000
    },
    {
        "month": "Apr",
        "investment": 200000,
        "sell": 423,
        "revenue": 24500,
        "stock": 550000
    },
    {
        "month": "May",
        "investment": 500000,
        "sell": 726,
        "revenue": 67010,
        "stock": 2150000
    },
    {
        "month": "Jun",
        "investment": 500000,
        "sell": 529,
        "revenue": 40405,
        "stock": 95000
    },
    {
        "month": "Jul",
        "investment": 600000,
        "sell": 601,
        "revenue": 50900,
        "stock": 450000
    },
    {
        "month": "Aug",
        "investment": 700000,
        "sell": 670,
        "revenue": 61000,
        "stock": 999000
    }
]